graph_search/__init__.py
graph_search/islands.py
graph_search/maze_analysis.py
graph_search/rope_analysis.py
graph_search/simple.py
graph_search/streetlearn_analysis.py
graph_search-0.1.0.dist-info/LICENSE
graph_search-0.1.0.dist-info/METADATA
graph_search-0.1.0.dist-info/WHEEL
graph_search-0.1.0.dist-info/top_level.txt
graph_search-0.1.0.dist-info/RECORD
