Metadata-Version: 2.1
Name: graph-search
Version: 0.1.0
Summary: graph-search
Home-page: https://github.com/geyang/graph_search
Author: Ge Yang<ge.ike.yang@gmail.com>
Author-email: ge.ike.yang@gmail.com
License: UNKNOWN
Platform: UNKNOWN
Requires-Dist: jupyter
Requires-Dist: matplotlib
Requires-Dist: ml-logger
Requires-Dist: networkx
Requires-Dist: numpy
Requires-Dist: pandas
Requires-Dist: waterbear
